LICENSE
README.md
spotiflite.py
spotiflite-1.0.0.dist-info/entry_points.txt
spotiflite-1.0.0.dist-info/LICENSE
spotiflite-1.0.0.dist-info/WHEEL
spotiflite-1.0.0.dist-info/METADATA
spotiflite-1.0.0.dist-info/RECORD
