Metadata-Version: 2.1
Name: spotiflite
Version: 1.0.0
Summary: scrapes spotify starting from an artist id, stores in sqlite
Home-page: https://github.com/sloev/spotiflite
License: MIT
Keywords: spotify,scraping,sqlite
Author: sloev
Author-email: johannes.valbjorn@gmail.com
Requires-Python: >=3.7,<4.0
Classifier: Intended Audience :: Developers
Classifier: License :: OSI Approved :: MIT License
Classifier: Natural Language :: English
Classifier: Programming Language :: Python :: 3
Classifier: Programming Language :: Python :: 3.7
Classifier: Programming Language :: Python :: 3.8
Requires-Dist: beautifulsoup4 (>=4.8.2,<5.0.0)
Requires-Dist: click (>=7.1.1,<8.0.0)
Requires-Dist: colorama (>=0.4.3,<0.5.0)
Requires-Dist: requests (>=2.23.0,<3.0.0)
Project-URL: Repository, https://github.com/sloev/spotiflite
